textLSP/__init__.py
textLSP/cli.py
textLSP/nn_utils.py
textLSP/server.py
textLSP/types.py
textLSP/utils.py
textLSP/workspace.py
textLSP/analysers/__init__.py
textLSP/analysers/analyser.py
textLSP/analysers/handler.py
textLSP/analysers/grammarbot/__init__.py
textLSP/analysers/grammarbot/grammarbot.py
textLSP/analysers/hf_checker/__init__.py
textLSP/analysers/hf_checker/hf_checker.py
textLSP/analysers/hf_completion/__init__.py
textLSP/analysers/hf_completion/hf_completion.py
textLSP/analysers/hf_instruction_checker/__init__.py
textLSP/analysers/hf_instruction_checker/hf_instruction_checker.py
textLSP/analysers/languagetool/__init__.py
textLSP/analysers/languagetool/languagetool.py
textLSP/analysers/ollama/__init__.py
textLSP/analysers/ollama/ollama.py
textLSP/analysers/openai/__init__.py
textLSP/analysers/openai/openai.py
textLSP/documents/__init__.py
textLSP/documents/document.py
textLSP/documents/latex/__init__.py
textLSP/documents/latex/latex.py
textLSP/documents/markdown/__init__.py
textLSP/documents/markdown/markdown.py
textLSP/documents/org/__init__.py
textLSP/documents/org/org.py
textLSP/documents/txt/__init__.py
textLSP/documents/txt/txt.py
textlsp-0.4.0.dist-info/licenses/LICENSE
textlsp-0.4.0.dist-info/METADATA
textlsp-0.4.0.dist-info/WHEEL
textlsp-0.4.0.dist-info/entry_points.txt
textlsp-0.4.0.dist-info/top_level.txt
textlsp-0.4.0.dist-info/RECORD
