Metadata-Version: 2.4
Name: textLSP
Version: 0.4.0
Summary: Language server for text spell and grammar check with various tools.
Home-page: https://github.com/hangyav/textLSP
Author: Viktor Hangya
Author-email: hangyav@gmail.com
License: GPLv3
Classifier: Programming Language :: Python :: 3
Classifier: License :: OSI Approved :: GNU General Public License v3 (GPLv3)
Classifier: Operating System :: OS Independent
License-File: LICENSE
Requires-Dist: pygls==2.0.0
Requires-Dist: lsprotocol==2025.0.0
Requires-Dist: language-tool-python==3.1.0
Requires-Dist: tree_sitter==0.21.3
Requires-Dist: gitpython==3.1.45
Requires-Dist: appdirs==1.4.4
Requires-Dist: openai==2.8.1
Requires-Dist: sortedcontainers==2.4.0
Requires-Dist: langdetect==1.0.9
Requires-Dist: ollama==0.6.1
Provides-Extra: dev
Requires-Dist: pytest==9.0.1; extra == "dev"
Requires-Dist: python-lsp-jsonrpc==1.1.2; extra == "dev"
Requires-Dist: pytest-cov==7.0.0; extra == "dev"
Requires-Dist: coverage-threshold==0.6.2; extra == "dev"
Provides-Extra: transformers
Requires-Dist: torch==2.9.1; extra == "transformers"
Requires-Dist: transformers==4.57.3; extra == "transformers"
Requires-Dist: bitsandbytes==0.48.2; extra == "transformers"
Dynamic: author
Dynamic: author-email
Dynamic: classifier
Dynamic: description
Dynamic: description-content-type
Dynamic: home-page
Dynamic: license
Dynamic: license-file
Dynamic: provides-extra
Dynamic: requires-dist
Dynamic: summary
